LICENSE
MANIFEST.in
README.md
setup.py
geobrowser_plugin/__init__.py
geobrowser_plugin/extraction.py
geobrowser_plugin/population.py
geobrowser_plugin/rest.py
geobrowser_plugin/utils.py
geobrowser_plugin/external_web_client/favicon.ico
geobrowser_plugin/external_web_client/index.html
geobrowser_plugin/external_web_client/css/app.55547781.css
geobrowser_plugin/external_web_client/css/chunk-vendors.23f7fa10.css
geobrowser_plugin/external_web_client/fonts/materialdesignicons-webfont.848935b0.woff
geobrowser_plugin/external_web_client/fonts/materialdesignicons-webfont.84cd5ee6.eot
geobrowser_plugin/external_web_client/fonts/materialdesignicons-webfont.c774cc6f.woff2
geobrowser_plugin/external_web_client/fonts/materialdesignicons-webfont.f6e66652.ttf
geobrowser_plugin/external_web_client/js/app.78dfc629.js
geobrowser_plugin/external_web_client/js/app.78dfc629.js.map
geobrowser_plugin/external_web_client/js/chunk-vendors.f2060889.js
geobrowser_plugin/external_web_client/js/chunk-vendors.f2060889.js.map
girder_geobrowser.egg-info/PKG-INFO
girder_geobrowser.egg-info/SOURCES.txt
girder_geobrowser.egg-info/dependency_links.txt
girder_geobrowser.egg-info/entry_points.txt
girder_geobrowser.egg-info/requires.txt
girder_geobrowser.egg-info/top_level.txt