Metadata-Version: 2.1
Name: girder-geobrowser
Version: 0.4.7
Summary: Map-oriented custom Girder appfor geospatial metadata browsing
Home-page: https://github.com/girder/geo_browser
Maintainer: Kitware, Inc.
Maintainer-email: kitware@kitware.com
License: UNKNOWN
Platform: UNKNOWN
